{
    "name": "rrel_entity",
    "roles": [
        "rrel_entity"
    ],
    "lookups": [
        "free-text",
        "keywords"
    ],
    "keywords": [
        {
            "keyword": "\u0412\u0438\u0442\u0430\u043b\u0438\u0439 \u0421\u0435\u0440\u0433\u0435\u0435\u0432\u0438\u0447",
            "synonyms": [
                "\u0412\u0438\u0442\u0430\u043b\u0438\u0439 \u0421\u0435\u0440\u0433\u0435\u0435\u0432\u0438\u0447"
            ]
        },
        {
            "keyword": "\u0414\u043c\u0438\u0442\u0440\u0438\u044f \u041b\u0435\u043e\u043d\u0438\u0434\u043e\u0432\u0438\u0447\u0430",
            "synonyms": [
                "\u0414\u043c\u0438\u0442\u0440\u0438\u044f \u041b\u0435\u043e\u043d\u0438\u0434\u043e\u0432\u0438\u0447\u0430"
            ]
        },
        {
            "keyword": "\u0418\u0432\u0430\u043d \u0414\u043c\u0438\u0442\u0440\u0438\u0435\u0432\u0438\u0447",
            "synonyms": [
                "\u0418\u0432\u0430\u043d \u0414\u043c\u0438\u0442\u0440\u0438\u0435\u0432\u0438\u0447"
            ]
        }
    ]
}
